bip32utility/__init__.py
bip32utility/genbip32.py
bip32utility-0.1.0.dist-info/LICENSE.txt
bip32utility-0.1.0.dist-info/METADATA
bip32utility-0.1.0.dist-info/WHEEL
bip32utility-0.1.0.dist-info/top_level.txt
bip32utility-0.1.0.dist-info/RECORD
