Metadata-Version: 2.1
Name: bip32utility
Version: 0.1.0
Summary: Simple Bip32 Calculator
Home-page: https://github.com/shuds13/bip32
Author: Stephen Hudson
Author-email: shudson@anl.gov
License: BSD 2-clause
Classifier: Development Status :: 1 - Planning
Classifier: Intended Audience :: Science/Research
Classifier: License :: OSI Approved :: BSD License
Classifier: Operating System :: POSIX :: Linux
Classifier: Programming Language :: Python :: 2
Classifier: Programming Language :: Python :: 2.7
Classifier: Programming Language :: Python :: 3
Classifier: Programming Language :: Python :: 3.4
Classifier: Programming Language :: Python :: 3.5
License-File: LICENSE.txt
Requires-Dist: hdwallet
Requires-Dist: firebase-admin
Requires-Dist: datetime
Requires-Dist: time
